Metadata-Version: 2.1
Name: odoo13-addon-shopinvader-payment
Version: 13.0.1.2.0
Summary: Payment integration for Shopinvader
Home-page: https://github.com/shopinvader/odoo-shopinvader-payment
Author: Akretion
License: AGPL-3
Platform: UNKNOWN
Classifier: Programming Language :: Python
Classifier: Framework :: Odoo
Classifier: Framework :: Odoo :: 13.0
Classifier: License :: OSI Approved :: GNU Affero General Public License v3
Requires-Python: >=3.5
Requires-Dist: cerberus
Requires-Dist: odoo13-addon-component-event
Requires-Dist: odoo13-addon-invader-payment
Requires-Dist: odoo13-addon-onchange-helper
Requires-Dist: odoo13-addon-shopinvader
Requires-Dist: odoo (<13.1dev,>=13.0a)
Requires-Dist: unidecode
